src/__init__.py
src/_version.py
src/parser.py
src/server.py
llms_txt_mcp-0.2.0.dist-info/METADATA
llms_txt_mcp-0.2.0.dist-info/WHEEL
llms_txt_mcp-0.2.0.dist-info/entry_points.txt
llms_txt_mcp-0.2.0.dist-info/licenses/LICENSE
llms_txt_mcp-0.2.0.dist-info/RECORD
