Metadata-Version: 2.4
Name: llms-txt-mcp
Version: 0.2.0
Summary: Lean MCP server for minimal-context docs via llms.txt
Project-URL: Homepage, https://github.com/tenequm/llms-mcp-txt
Project-URL: Repository, https://github.com/tenequm/llms-mcp-txt
Project-URL: Issues, https://github.com/tenequm/llms-mcp-txt/issues
Author-email: Misha Kolesnik <misha@kolesnik.io>
License: MIT
License-File: LICENSE
Keywords: claude code,documentation,llms.txt,mcp,model context protocol,semantic search
Classifier: Intended Audience :: Developers
Classifier: License :: OSI Approved :: MIT License
Classifier: Operating System :: OS Independent
Classifier: Programming Language :: Python :: 3
Classifier: Programming Language :: Python :: 3.12
Classifier: Topic :: Software Development :: Build Tools
Classifier: Topic :: Software Development :: Libraries :: Application Frameworks
Requires-Python: >=3.12
Requires-Dist: chromadb>=0.5.0
Requires-Dist: httpx>=0.27.0
Requires-Dist: mcp[cli]>=1.12.0
Requires-Dist: pydantic>=2.0.0
Requires-Dist: pyyaml>=6.0.0
Requires-Dist: sentence-transformers>=3.0.0
Provides-Extra: dev
Requires-Dist: mypy>=1.11.0; extra == 'dev'
Requires-Dist: pytest-asyncio>=0.23.0; extra == 'dev'
Requires-Dist: pytest>=8.0.0; extra == 'dev'
Requires-Dist: ruff>=0.6.0; extra == 'dev'
